as_client/__init__.py
as_client/__main__.py
as_client/client.py
as_client/exceptions.py
as_client/model.py
as_client/util.py
as_client/version.py
test/__init__.py
test/test_documents.py
test/test_workflows.py
as_client-2.22.0.dist-info/METADATA
as_client-2.22.0.dist-info/WHEEL
as_client-2.22.0.dist-info/top_level.txt
as_client-2.22.0.dist-info/RECORD
