Metadata-Version: 2.1
Name: as_client
Version: 2.22.0
Summary: Analysis Services Client
Home-page: https://bitbucket.csiro.au/projects/SC/repos/as-client-python/browse
Author: Mac Coombe
Author-email: Mac Coombe <mac.coombe@csiro.au>
Project-URL: Homepage, https://bitbucket.csiro.au/projects/SC/repos/as-client-python/browse
Keywords: Analysis-Services
Classifier: Development Status :: 3 - Alpha
Classifier: Topic :: Scientific/Engineering :: Information Analysis
Classifier: Intended Audience :: Developers
Classifier: Natural Language :: English
Classifier: Operating System :: POSIX
Classifier: Programming Language :: Python :: 2.7
Requires-Python: >=2.7
Requires-Dist: requests>=2.11.1
Provides-Extra: test
Requires-Dist: responses<1.0.0,>=0.13.2; extra == "test"
